{"tkk-009":"en/tk/k-/00/en-tkk-009.html","toen-056":"en/to/en/-0/en-toen-056.html","tkk-010":"en/tk/k-/01/en-tkk-010.html","tmy-003":"en/tm/y-/00/en-tmy-003.html","thnib-082":"en/th/ni/b-/en-thnib-082.html","thtp-053":"en/th/tp/-0/en-thtp-053.html","thtp-052":"en/th/tp/-0/en-thtp-052.html","t28-608":"en/t2/8-/60/en-t28-608.html","tyvm-211":"en/ty/vm/-2/en-tyvm-211.html","tyvm-212":"en/ty/vm/-2/en-tyvm-212.html","tr-2131":"en/tr/-2/13/en-tr-2131.html","tppn-212":"en/tp/pn/-2/en-tppn-212.html","tyvm-214":"en/ty/vm/-2/en-tyvm-214.html","tar0014":"en/ta/r0/01/en-tar0014.html","tar0013":"en/ta/r0/01/en-tar0013.html","tar0012":"en/ta/r0/01/en-tar0012.html","tar0010":"en/ta/r0/01/en-tar0010.html","tar0009":"en/ta/r0/00/en-tar0009.html","tar0007":"en/ta/r0/00/en-tar0007.html","tar0005":"en/ta/r0/00/en-tar0005.html","tar0004":"en/ta/r0/00/en-tar0004.html","tkmj-001":"en/tk/mj/-0/en-tkmj-001.html","tmen-001":"en/tm/en/-0/en-tmen-001.html","tue-119":"en/tu/e-/11/en-tue-119.html","ten-039":"en/te/n-/03/en-ten-039.html","tokyo-539":"en/to/ky/o-/en-tokyo-539.html","ttjm-101":"en/tt/jm/-1/en-ttjm-101.html","tsp-449":"en/ts/p-/44/en-tsp-449.html","tpin-019":"en/tp/in/-0/en-tpin-019.html","tpin-020":"en/tp/in/-0/en-tpin-020.html","tkkv-002":"en/tk/kv/-0/en-tkkv-002.html","toen-057":"en/to/en/-0/en-toen-057.html","tat-037":"en/ta/t-/03/en-tat-037.html","tat-036":"en/ta/t-/03/en-tat-036.html","tat-035":"en/ta/t-/03/en-tat-035.html","tat-043":"en/ta/t-/04/en-tat-043.html","tat-040":"en/ta/t-/04/en-tat-040.html","tks-002-2":"en/tk/s-/00/en-tks-002-2.html","tat-033":"en/ta/t-/03/en-tat-033.html","tat-034":"en/ta/t-/03/en-tat-034.html","tat-041":"en/ta/t-/04/en-tat-041.html","tat-042":"en/ta/t-/04/en-tat-042.html","tat-032":"en/ta/t-/03/en-tat-032.html","tks-003-2":"en/tk/s-/00/en-tks-003-2.html","tat-044":"en/ta/t-/04/en-tat-044.html","tkd-001-2":"en/tk/d-/00/en-tkd-001-2.html","tat-038":"en/ta/t-/03/en-tat-038.html","tat-039":"en/ta/t-/03/en-tat-039.html","tat-031":"en/ta/t-/03/en-tat-031.html","tat-073":"en/ta/t-/07/en-tat-073.html","tat-072":"en/ta/t-/07/en-tat-072.html","tat-070":"en/ta/t-/07/en-tat-070.html","tat-069":"en/ta/t-/06/en-tat-069.html","tat-068":"en/ta/t-/06/en-tat-068.html","tat-066":"en/ta/t-/06/en-tat-066.html","tat-065":"en/ta/t-/06/en-tat-065.html","tat-064":"en/ta/t-/06/en-tat-064.html","tat-063":"en/ta/t-/06/en-tat-063.html","tat-062":"en/ta/t-/06/en-tat-062.html","tat-061":"en/ta/t-/06/en-tat-061.html","tat-060":"en/ta/t-/06/en-tat-060.html","tat-030":"en/ta/t-/03/en-tat-030.html","tat-059":"en/ta/t-/05/en-tat-059.html","tac-001":"en/ta/c-/00/en-tac-001.html","tat-024":"en/ta/t-/02/en-tat-024.html","tks-006-2":"en/tk/s-/00/en-tks-006-2.html","tks-005":"en/tk/s-/00/en-tks-005.html","tat-058":"en/ta/t-/05/en-tat-058.html","tat-057":"en/ta/t-/05/en-tat-057.html","tat-056":"en/ta/t-/05/en-tat-056.html","tat-055":"en/ta/t-/05/en-tat-055.html","tat-018":"en/ta/t-/01/en-tat-018.html","tat-001-2":"en/ta/t-/00/en-tat-001-2.html","tat-048":"en/ta/t-/04/en-tat-048.html","tat-004-2":"en/ta/t-/00/en-tat-004-2.html","tat-054":"en/ta/t-/05/en-tat-054.html","tat-049":"en/ta/t-/04/en-tat-049.html","tat-052":"en/ta/t-/05/en-tat-052.html","tat-046":"en/ta/t-/04/en-tat-046.html","tat-006-2":"en/ta/t-/00/en-tat-006-2.html","tat-045":"en/ta/t-/04/en-tat-045.html","tat-050":"en/ta/t-/05/en-tat-050.html","tat-047":"en/ta/t-/04/en-tat-047.html","tat-003-2":"en/ta/t-/00/en-tat-003-2.html","tat-005-2":"en/ta/t-/00/en-tat-005-2.html","tny-001":"en/tn/y-/00/en-tny-001.html","tat-007":"en/ta/t-/00/en-tat-007.html","tat-051":"en/ta/t-/05/en-tat-051.html","tks-004":"en/tk/s-/00/en-tks-004.html","tat-002-2":"en/ta/t-/00/en-tat-002-2.html","tat-053":"en/ta/t-/05/en-tat-053.html","tyvm-218":"en/ty/vm/-2/en-tyvm-218.html","tppn-214":"en/tp/pn/-2/en-tppn-214.html","tppn-213":"en/tp/pn/-2/en-tppn-213.html","tnoz-010":"en/tn/oz/-0/en-tnoz-010.html","tikb-128":"en/ti/kb/-1/en-tikb-128.html","tikp-064":"en/ti/kp/-0/en-tikp-064.html","tikb-127":"en/ti/kb/-1/en-tikb-127.html","tmen-002":"en/tm/en/-0/en-tmen-002.html","thnib-083":"en/th/ni/b-/en-thnib-083.html","tomnvd-004":"en/to/mn/vd/en-tomnvd-004.html","twav-d001":"en/tw/av/-d/en-twav-d001.html","twav-s02":"en/tw/av/-s/en-twav-s02.html","twav-s01":"en/tw/av/-s/en-twav-s01.html","tyvm-220":"en/ty/vm/-2/en-tyvm-220.html","tyan-005":"en/ty/an/-0/en-tyan-005.html","thtp-056":"en/th/tp/-0/en-thtp-056.html","thtp-055":"en/th/tp/-0/en-thtp-055.html","t28-609":"en/t2/8-/60/en-t28-609.html","tr-2136":"en/tr/-2/13/en-tr-2136.html","tr-2134":"en/tr/-2/13/en-tr-2134.html","tmy-004":"en/tm/y-/00/en-tmy-004.html","tyvm-221":"en/ty/vm/-2/en-tyvm-221.html","tyvm-222":"en/ty/vm/-2/en-tyvm-222.html","toen-059":"en/to/en/-0/en-toen-059.html","tanp-006":"en/ta/np/-0/en-tanp-006.html","tsm-028":"en/ts/m-/02/en-tsm-028.html","tue-120":"en/tu/e-/12/en-tue-120.html","toen-060":"en/to/en/-0/en-toen-060.html","tyvm-223":"en/ty/vm/-2/en-tyvm-223.html","tyvm-224":"en/ty/vm/-2/en-tyvm-224.html","ttjk-015":"en/tt/jk/-0/en-ttjk-015.html","tsp-450":"en/ts/p-/45/en-tsp-450.html","tanp-007":"en/ta/np/-0/en-tanp-007.html","tpin-022":"en/tp/in/-0/en-tpin-022.html","tpin-021":"en/tp/in/-0/en-tpin-021.html","tkmj-002":"en/tk/mj/-0/en-tkmj-002.html","tt003":"en/tt/00/3/en-tt003.html","taxd-009":"en/ta/xd/-0/en-taxd-009.html","tkk-011":"en/tk/k-/01/en-tkk-011.html","tyvm-225":"en/ty/vm/-2/en-tyvm-225.html","tyvm-226":"en/ty/vm/-2/en-tyvm-226.html","tomn-198":"en/to/mn/-1/en-tomn-198.html","tppn-215":"en/tp/pn/-2/en-tppn-215.html","tppn-216":"en/tp/pn/-2/en-tppn-216.html","tnoz-011":"en/tn/oz/-0/en-tnoz-011.html","tikb-129":"en/ti/kb/-1/en-tikb-129.html","tikp-065":"en/ti/kp/-0/en-tikp-065.html","tikb-130":"en/ti/kb/-1/en-tikb-130.html","tm0156":"en/tm/01/56/en-tm0156.html","tmw010":"en/tm/w0/10/en-tmw010.html","tm0157":"en/tm/01/57/en-tm0157.html","toen-061":"en/to/en/-0/en-toen-061.html","tyvm-227":"en/ty/vm/-2/en-tyvm-227.html","tyvm-228":"en/ty/vm/-2/en-tyvm-228.html","totte-034":"en/to/tt/e-/en-totte-034.html","tmen-004":"en/tm/en/-0/en-tmen-004.html","totte-035":"en/to/tt/e-/en-totte-035.html","tm0159":"en/tm/01/59/en-tm0159.html","tm0158":"en/tm/01/58/en-tm0158.html","totte-036":"en/to/tt/e-/en-totte-036.html","taxd-010":"en/ta/xd/-0/en-taxd-010.html","tkkv-003":"en/tk/kv/-0/en-tkkv-003.html","tkk-012":"en/tk/k-/01/en-tkk-012.html","tmw011":"en/tm/w0/11/en-tmw011.html","toen-062":"en/to/en/-0/en-toen-062.html","tyvm-229":"en/ty/vm/-2/en-tyvm-229.html","tyvm-230":"en/ty/vm/-2/en-tyvm-230.html","tr-2203":"en/tr/-2/20/en-tr-2203.html","tr-2201":"en/tr/-2/20/en-tr-2201.html","tr-2202":"en/tr/-2/20/en-tr-2202.html","thtp-058":"en/th/tp/-0/en-thtp-058.html","thtp-057":"en/th/tp/-0/en-thtp-057.html","t28-610":"en/t2/8-/61/en-t28-610.html","tmen-005":"en/tm/en/-0/en-tmen-005.html","tm0160":"en/tm/01/60/en-tm0160.html","tm0161":"en/tm/01/61/en-tm0161.html","tsm-029":"en/ts/m-/02/en-tsm-029.html","thp-081":"en/th/p-/08/en-thp-081.html","tbb-090":"en/tb/b-/09/en-tbb-090.html","tmw012":"en/tm/w0/12/en-tmw012.html","tmf001":"en/tm/f0/01/en-tmf001.html","tyvm-231":"en/ty/vm/-2/en-tyvm-231.html","tyvm-232":"en/ty/vm/-2/en-tyvm-232.html","tysf-003":"en/ty/sf/-0/en-tysf-003.html","tysf-002":"en/ty/sf/-0/en-tysf-002.html","tysf-001":"en/ty/sf/-0/en-tysf-001.html","tsp-451":"en/ts/p-/45/en-tsp-451.html","trk-001":"en/tr/k-/00/en-trk-001.html","tpin-024":"en/tp/in/-0/en-tpin-024.html","tpin-023":"en/tp/in/-0/en-tpin-023.html","tue-121":"en/tu/e-/12/en-tue-121.html","totte-037":"en/to/tt/e-/en-totte-037.html","totte-038":"en/to/tt/e-/en-totte-038.html","taxd-011":"en/ta/xd/-0/en-taxd-011.html","ten-040":"en/te/n-/04/en-ten-040.html","tkk-013":"en/tk/k-/01/en-tkk-013.html","tkkv-004":"en/tk/kv/-0/en-tkkv-004.html","tyvm-233":"en/ty/vm/-2/en-tyvm-233.html","tyvm-234":"en/ty/vm/-2/en-tyvm-234.html","tppn-219":"en/tp/pn/-2/en-tppn-219.html","tppn-217":"en/tp/pn/-2/en-tppn-217.html","tppn-218":"en/tp/pn/-2/en-tppn-218.html","tikp-066":"en/ti/kp/-0/en-tikp-066.html","tikb-132":"en/ti/kb/-1/en-tikb-132.html","tikb-131":"en/ti/kb/-1/en-tikb-131.html","tt007":"en/tt/00/7/en-tt007.html","tmen-006":"en/tm/en/-0/en-tmen-006.html","tkmj-003":"en/tk/mj/-0/en-tkmj-003.html","toen-063":"en/to/en/-0/en-toen-063.html","tyvm-235":"en/ty/vm/-2/en-tyvm-235.html","tyvm-236":"en/ty/vm/-2/en-tyvm-236.html","totte-040":"en/to/tt/e-/en-totte-040.html","totte-041":"en/to/tt/e-/en-totte-041.html","tanp-008":"en/ta/np/-0/en-tanp-008.html","totte-043":"en/to/tt/e-/en-totte-043.html","tmen-008":"en/tm/en/-0/en-tmen-008.html","totte-042":"en/to/tt/e-/en-totte-042.html","tkk-014":"en/tk/k-/01/en-tkk-014.html","tokyo-546":"en/to/ky/o-/en-tokyo-546.html","tmw013":"en/tm/w0/13/en-tmw013.html","tm0163":"en/tm/01/63/en-tm0163.html","tm0162":"en/tm/01/62/en-tm0162.html","toen-064":"en/to/en/-0/en-toen-064.html","tyvm-237":"en/ty/vm/-2/en-tyvm-237.html","tyvm-238":"en/ty/vm/-2/en-tyvm-238.html","thtp-059":"en/th/tp/-0/en-thtp-059.html","thtp-060":"en/th/tp/-0/en-thtp-060.html","t28-612":"en/t2/8-/61/en-t28-612.html","t28-611":"en/t2/8-/61/en-t28-611.html","tsds-42603":"en/ts/ds/-4/en-tsds-42603.html","tt008":"en/tt/00/8/en-tt008.html","tkmj-004":"en/tk/mj/-0/en-tkmj-004.html","tm0164":"en/tm/01/64/en-tm0164.html","tr-2204":"en/tr/-2/20/en-tr-2204.html","tr-2205":"en/tr/-2/20/en-tr-2205.html","thnib-085":"en/th/ni/b-/en-thnib-085.html","taxd-012":"en/ta/xd/-0/en-taxd-012.html","tm0165":"en/tm/01/65/en-tm0165.html","tsm-030":"en/ts/m-/03/en-tsm-030.html","tg-120":"en/tg/-1/20/en-tg-120.html","tmw014":"en/tm/w0/14/en-tmw014.html","tyvm-240":"en/ty/vm/-2/en-tyvm-240.html","tyvm-239":"en/ty/vm/-2/en-tyvm-239.html","tysf-004":"en/ty/sf/-0/en-tysf-004.html","tysf-005":"en/ty/sf/-0/en-tysf-005.html","tysf-006":"en/ty/sf/-0/en-tysf-006.html","tsp-452":"en/ts/p-/45/en-tsp-452.html","tpin-026":"en/tp/in/-0/en-tpin-026.html","tpin-025":"en/tp/in/-0/en-tpin-025.html","tue-122":"en/tu/e-/12/en-tue-122.html","tm0166":"en/tm/01/66/en-tm0166.html","tm0167":"en/tm/01/67/en-tm0167.html","tmw015":"en/tm/w0/15/en-tmw015.html","tkk-015":"en/tk/k-/01/en-tkk-015.html","tyvm-242":"en/ty/vm/-2/en-tyvm-242.html","tyvm-241":"en/ty/vm/-2/en-tyvm-241.html","tikb-133":"en/ti/kb/-1/en-tikb-133.html","tikb-134":"en/ti/kb/-1/en-tikb-134.html","tnoz-012":"en/tn/oz/-0/en-tnoz-012.html","tikp-067":"en/ti/kp/-0/en-tikp-067.html","tm0168":"en/tm/01/68/en-tm0168.html","tmen-009":"en/tm/en/-0/en-tmen-009.html","tm0169":"en/tm/01/69/en-tm0169.html","tmw016":"en/tm/w0/16/en-tmw016.html","toen-065":"en/to/en/-0/en-toen-065.html","tyvm-244":"en/ty/vm/-2/en-tyvm-244.html","tyvm-243":"en/ty/vm/-2/en-tyvm-243.html","tppn-221":"en/tp/pn/-2/en-tppn-221.html","tppn-222":"en/tp/pn/-2/en-tppn-222.html","tomn-199":"en/to/mn/-1/en-tomn-199.html","tppn-220":"en/tp/pn/-2/en-tppn-220.html","tanp-009":"en/ta/np/-0/en-tanp-009.html","tmg004":"en/tm/g0/04/en-tmg004.html","tkk-016":"en/tk/k-/01/en-tkk-016.html","tmen-010":"en/tm/en/-0/en-tmen-010.html","tmw018":"en/tm/w0/18/en-tmw018.html","tmg002":"en/tm/g0/02/en-tmg002.html","thnib-087":"en/th/ni/b-/en-thnib-087.html","totte-026":"en/to/tt/e-/en-totte-026.html","totte-027":"en/to/tt/e-/en-totte-027.html","tmw019":"en/tm/w0/19/en-tmw019.html","tmg003":"en/tm/g0/03/en-tmg003.html","thni-086":"en/th/ni/-0/en-thni-086.html","toen-066":"en/to/en/-0/en-toen-066.html","tmp-001":"en/tm/p-/00/en-tmp-001.html","tksc-064":"en/tk/sc/-0/en-tksc-064.html","tksc-067":"en/tk/sc/-0/en-tksc-067.html","tksc-030":"en/tk/sc/-0/en-tksc-030.html","tksc-019":"en/tk/sc/-0/en-tksc-019.html","tmen-011":"en/tm/en/-0/en-tmen-011.html","thtp-061":"en/th/tp/-0/en-thtp-061.html","tsds-42608":"en/ts/ds/-4/en-tsds-42608.html","tyvm-246":"en/ty/vm/-2/en-tyvm-246.html","thtp-062":"en/th/tp/-0/en-thtp-062.html","tyvm-245":"en/ty/vm/-2/en-tyvm-245.html","t28-615":"en/t2/8-/61/en-t28-615.html","t28-613":"en/t2/8-/61/en-t28-613.html","ten-043":"en/te/n-/04/en-ten-043.html","tgav-010":"en/tg/av/-0/en-tgav-010.html","tgav-004":"en/tg/av/-0/en-tgav-004.html","tgav-005":"en/tg/av/-0/en-tgav-005.html","tkwa-215":"en/tk/wa/-2/en-tkwa-215.html","tkwa-217":"en/tk/wa/-2/en-tkwa-217.html","tkwa-219":"en/tk/wa/-2/en-tkwa-219.html","tkwa-221":"en/tk/wa/-2/en-tkwa-221.html","tkwa-199":"en/tk/wa/-1/en-tkwa-199.html","tkwa-213":"en/tk/wa/-2/en-tkwa-213.html","tkwa-223":"en/tk/wa/-2/en-tkwa-223.html","tkwa-200":"en/tk/wa/-2/en-tkwa-200.html","tkwa-202":"en/tk/wa/-2/en-tkwa-202.html","tkwa-201":"en/tk/wa/-2/en-tkwa-201.html","tkwa-212":"en/tk/wa/-2/en-tkwa-212.html","tkwa-208":"en/tk/wa/-2/en-tkwa-208.html","tkwa-210":"en/tk/wa/-2/en-tkwa-210.html","tkwa-207":"en/tk/wa/-2/en-tkwa-207.html","tkwa-211":"en/tk/wa/-2/en-tkwa-211.html","tkwa-209":"en/tk/wa/-2/en-tkwa-209.html","tkwa-198":"en/tk/wa/-1/en-tkwa-198.html","tkwa-195":"en/tk/wa/-1/en-tkwa-195.html","tkwa-189":"en/tk/wa/-1/en-tkwa-189.html","tkwa-196":"en/tk/wa/-1/en-tkwa-196.html","tkwa-194":"en/tk/wa/-1/en-tkwa-194.html","tkwa-193":"en/tk/wa/-1/en-tkwa-193.html","tkwa-192":"en/tk/wa/-1/en-tkwa-192.html","tkwa-185":"en/tk/wa/-1/en-tkwa-185.html","tkwa-188":"en/tk/wa/-1/en-tkwa-188.html","tkwa-170":"en/tk/wa/-1/en-tkwa-170.html","tkwa-173":"en/tk/wa/-1/en-tkwa-173.html","tkwa-172":"en/tk/wa/-1/en-tkwa-172.html","tkwa-171":"en/tk/wa/-1/en-tkwa-171.html","tls-007":"en/tl/s-/00/en-tls-007.html","tdsu-069":"en/td/su/-0/en-tdsu-069.html","tdsu-053":"en/td/su/-0/en-tdsu-053.html","tem-007":"en/te/m-/00/en-tem-007.html","tbl-073":"en/tb/l-/07/en-tbl-073.html","touj-307":"en/to/uj/-3/en-touj-307.html","tkpr-003":"en/tk/pr/-0/en-tkpr-003.html","tkpr-002":"en/tk/pr/-0/en-tkpr-002.html","tfg-010":"en/tf/g-/01/en-tfg-010.html","tms-010":"en/tm/s-/01/en-tms-010.html","tatb-003":"en/ta/tb/-0/en-tatb-003.html","tre-181":"en/tr/e-/18/en-tre-181.html","tus-106":"en/tu/s-/10/en-tus-106.html","tus-105":"en/tu/s-/10/en-tus-105.html","tre-159":"en/tr/e-/15/en-tre-159.html","tre-162":"en/tr/e-/16/en-tre-162.html","tre-164":"en/tr/e-/16/en-tre-164.html","tre-176":"en/tr/e-/17/en-tre-176.html","tus-104":"en/tu/s-/10/en-tus-104.html","tre-174":"en/tr/e-/17/en-tre-174.html","tus-103":"en/tu/s-/10/en-tus-103.html","tus-102":"en/tu/s-/10/en-tus-102.html","tus-101":"en/tu/s-/10/en-tus-101.html","tus-100":"en/tu/s-/10/en-tus-100.html","tus-099":"en/tu/s-/09/en-tus-099.html","tus-098":"en/tu/s-/09/en-tus-098.html","tus-097":"en/tu/s-/09/en-tus-097.html","tus-096":"en/tu/s-/09/en-tus-096.html","tus-095":"en/tu/s-/09/en-tus-095.html"}